.coveragerc
AUTHORS
CHANGES.rst
CONTRIBUTING.rst
LICENSE
MANIFEST.in
README.rst
RELEASE.rst
manage.py
runtests.py
setup.py
tox.ini
django_mailer_ulamlabs.egg-info/PKG-INFO
django_mailer_ulamlabs.egg-info/SOURCES.txt
django_mailer_ulamlabs.egg-info/dependency_links.txt
django_mailer_ulamlabs.egg-info/requires.txt
django_mailer_ulamlabs.egg-info/top_level.txt
docs/index.rst
docs/usage.rst
mailer/__init__.py
mailer/admin.py
mailer/backend.py
mailer/engine.py
mailer/models.py
mailer/tests.py
mailer/locale/ru/LC_MESSAGES/django.po
mailer/management/__init__.py
mailer/management/helpers.py
mailer/management/commands/__init__.py
mailer/management/commands/purge_mail_log.py
mailer/management/commands/retry_deferred.py
mailer/management/commands/send_mail.py
mailer/migrations/0001_initial.py
mailer/migrations/0002_auto_20150720_1433.py
mailer/migrations/0003_messagelog_message_id.py
mailer/migrations/0004_messagelog_to_emails.py
mailer/migrations/0005_message_to_emails.py
mailer/migrations/__init__.py
mailer/south_migrations/0001_initial.py
mailer/south_migrations/0002_auto__chg_field_dontsendentry_to_address.py
mailer/south_migrations/__init__.py