Metadata-Version: 1.1
Name: django-mailer-ulamlabs
Version: 1.2.4
Summary: A reusable Django app for queuing the sending of email
Home-page: http://github.com/pinax/django-mailer/
Author: Pinax Team
Author-email: developers@pinaxproject.com
License: UNKNOWN
Platform: UNKNOWN
Classifier: Development Status :: 5 - Production/Stable
Classifier: Environment :: Web Environment
Classifier: Intended Audience :: Developers
Classifier: License :: OSI Approved :: MIT License
Classifier: Operating System :: OS Independent
Classifier: Programming Language :: Python
Classifier: Programming Language :: Python :: 2.7
Classifier: Programming Language :: Python :: 3.3
Classifier: Framework :: Django
